token_counter/__init__.py
token_counter/__main__.py
token_counter/cli.py
token_counter/counter.py
token_counter/config/allowed_extensions.json
token_counter/config/llm_limits.json
token_counter_cli-0.1.4.dist-info/licenses/LICENSE
token_counter_cli-0.1.4.dist-info/METADATA
token_counter_cli-0.1.4.dist-info/WHEEL
token_counter_cli-0.1.4.dist-info/entry_points.txt
token_counter_cli-0.1.4.dist-info/top_level.txt
token_counter_cli-0.1.4.dist-info/RECORD
