Metadata-Version: 2.4
Name: token-counter-cli
Version: 0.1.4
Summary: A fast, user-friendly CLI tool to count tokens in text files using tiktoken, with LLM context limit comparison and rich formatting.
Author-email: Puya <puya@example.com>
License-Expression: MIT
Project-URL: Homepage, https://github.com/puya/token-counter-cli
Project-URL: Repository, https://github.com/puya/token-counter-cli
Project-URL: Issues, https://github.com/puya/token-counter-cli/issues
Keywords: cli,tokens,tiktoken,openai,llm,text-analysis
Classifier: Development Status :: 4 - Beta
Classifier: Intended Audience :: Developers
Classifier: Operating System :: OS Independent
Classifier: Programming Language :: Python :: 3
Classifier: Programming Language :: Python :: 3.10
Classifier: Topic :: Software Development :: Libraries :: Python Modules
Classifier: Topic :: Text Processing
Classifier: Topic :: Utilities
Requires-Python: >=3.10
License-File: LICENSE
Requires-Dist: inquirerpy>=0.3.4
Requires-Dist: rich>=14.0.0
Requires-Dist: tiktoken>=0.9.0
Requires-Dist: typer>=0.16.0
Dynamic: license-file
